hdfq/__init__.py
hdfq/__main__.py
hdfq/cli/__init__.py
hdfq/cli/app.py
hdfq/cli/tools.py
hdfq/display.py
hdfq/evaluation.py
hdfq/exceptions.py
hdfq/grammar.ebnf
hdfq/hdfq.py
hdfq/lexer.py
hdfq/parser.py
hdfq/repair.py
hdfq/syntax.py
hdfq/tokens.py
hdfq-0.4.2.dist-info/licenses/LICENSE
hdfq-0.4.2.dist-info/WHEEL
hdfq-0.4.2.dist-info/entry_points.txt
hdfq-0.4.2.dist-info/METADATA
hdfq-0.4.2.dist-info/RECORD
