Metadata-Version: 2.4
Name: hdfq
Version: 0.4.2
Summary: Command-line HDF5 processor
Author: Matteo Bouvier
Author-email: Matteo Bouvier <matteo.bouvier@hotmail.fr>
License-Expression: MIT
License-File: LICENSE
Classifier: Development Status :: 5 - Production/Stable
Classifier: Environment :: Console
Classifier: Intended Audience :: Developers
Classifier: Intended Audience :: Education
Classifier: Intended Audience :: Science/Research
Classifier: License :: OSI Approved :: MIT License
Classifier: Programming Language :: Python :: 3.12
Classifier: Programming Language :: Python :: 3.13
Classifier: Programming Language :: Python :: 3.14
Classifier: Topic :: Scientific/Engineering
Classifier: Topic :: Utilities
Classifier: Typing :: Typed
Requires-Dist: typer>=0.9.0
Requires-Dist: rich>=13.7.1
Requires-Dist: ch5mpy>=0.4.6
Requires-Python: >=3.12
Project-URL: Homepage, https://github.com/MatteoBouvier/hdfq
